configleaf/__init__.py
configleaf-0.0.1.dist-info/LICENSE.txt
configleaf-0.0.1.dist-info/METADATA
configleaf-0.0.1.dist-info/WHEEL
configleaf-0.0.1.dist-info/top_level.txt
configleaf-0.0.1.dist-info/RECORD
